setup.py
distributions_test_from_argentina/Binomialdistribution.py
distributions_test_from_argentina/Gaussiandistribution.py
distributions_test_from_argentina/Generaldistribution.py
distributions_test_from_argentina/__init__.py
distributions_test_from_argentina.egg-info/PKG-INFO
distributions_test_from_argentina.egg-info/SOURCES.txt
distributions_test_from_argentina.egg-info/dependency_links.txt
distributions_test_from_argentina.egg-info/not-zip-safe
distributions_test_from_argentina.egg-info/top_level.txt